Metadata-Version: 2.1
Name: hydrodel
Version: 0.0.1
Summary: Python package for surface water mapping and delineation.
Home-page: https://github.com/lukmanfash/hydrodel
Author: Lukman Fashina
Author-email: lukmanfashina@yahoo.com
License: MIT license
Keywords: hydrodel
Classifier: Development Status :: 2 - Pre-Alpha
Classifier: Intended Audience :: Developers
Classifier: License :: OSI Approved :: MIT License
Classifier: Natural Language :: English
Classifier: Programming Language :: Python :: 3
Classifier: Programming Language :: Python :: 3.7
Classifier: Programming Language :: Python :: 3.8
Classifier: Programming Language :: Python :: 3.9
Classifier: Programming Language :: Python :: 3.10
Requires-Python: >=3.7
License-File: LICENSE
